maia_hdl/__init__.py
maia_hdl/axi.py
maia_hdl/axi4_lite.py
maia_hdl/buffer.py
maia_hdl/cdc.py
maia_hdl/clknx.py
maia_hdl/cmult.py
maia_hdl/config.py
maia_hdl/configs.py
maia_hdl/cpwr.py
maia_hdl/ddc.py
maia_hdl/dma.py
maia_hdl/fft.py
maia_hdl/fifo.py
maia_hdl/fir.py
maia_hdl/floating_point.py
maia_hdl/maia_sdr.py
maia_hdl/maia_sdr_version.py
maia_hdl/mixer.py
maia_hdl/mult2x.py
maia_hdl/packer.py
maia_hdl/pluto_platform.py
maia_hdl/pulse.py
maia_hdl/recorder.py
maia_hdl/register.py
maia_hdl/spectrometer.py
maia_hdl/spectrum_integrator.py
maia_hdl/util.py
maia_hdl-0.6.2.dist-info/METADATA
maia_hdl-0.6.2.dist-info/WHEEL
maia_hdl-0.6.2.dist-info/licenses/LICENSE
maia_hdl-0.6.2.dist-info/RECORD
