Metadata-Version: 2.4
Name: maia_hdl
Version: 0.6.2
Summary: Maia SDR FPGA Amaranth HDL code
Project-URL: Homepage, https://maia-sdr.org/
Project-URL: Bug Tracker, https://github.com/maia-sdr/maia-sdr/issues
Project-URL: Source Code, https://github.com/maia-sdr/maia-sdr
Author-email: Daniel Estevez <daniel@destevez.net>
Maintainer-email: Daniel Estevez <daniel@destevez.net>
License-File: LICENSE
Classifier: License :: OSI Approved :: MIT License
Classifier: Operating System :: OS Independent
Classifier: Programming Language :: Python :: 3
Classifier: Topic :: Communications :: Ham Radio
Classifier: Topic :: Scientific/Engineering
Classifier: Topic :: Scientific/Engineering :: Electronic Design Automation (EDA)
Requires-Python: >=3.9
Requires-Dist: amaranth<0.6,>=0.5
Requires-Dist: numpy
Requires-Dist: scipy
